{"results": [{"dataset": "aster30m", "elevation": 731.0, "location": {"lat": -23.526187, "lng": -46.648558}}, {"dataset": "aster30m", "elevation": 738.0, "location": {"lat": -23.550238, "lng": -46.606854}}, {"dataset": "aster30m", "elevation": 736.0, "location": {"lat": -23.548556, "lng": -46.62971}}, {"dataset": "aster30m", "elevation": 734.0, "location": {"lat": -23.548844, "lng": -46.63042}}, {"dataset": "aster30m", "elevation": 758.0, "location": {"lat": -23.541022, "lng": -46.646556}}, {"dataset": "aster30m", "elevation": 793.0, "location": {"lat": -23.545281, "lng": -46.675459}}, {"dataset": "aster30m", "elevation": 790.0, "location": {"lat": -23.54526, "lng": -46.676079}}, {"dataset": "aster30m", "elevation": 795.0, "location": {"lat": -23.548917, "lng": -46.674877}}, {"dataset": "aster30m", "elevation": 822.0, "location": {"lat": -23.555469, "lng": -46.667475}}, {"dataset": "aster30m", "elevation": 824.0, "location": {"lat": -23.553142, "lng": -46.661721}}, {"dataset": "aster30m", "elevation": 817.0, "location": {"lat": -23.554697, "lng": -46.664403}}, {"dataset": "aster30m", "elevation": 800.0, "location": {"lat": -23.550346, "lng": -46.660001}}, {"dataset": "aster30m", "elevation": 761.0, "location": {"lat": -23.547974, "lng": -46.670972}}, {"dataset": "aster30m", "elevation": 745.0, "location": {"lat": -23.551899, "lng": -46.647388}}, {"dataset": "aster30m", "elevation": 795.0, "location": {"lat": -23.568002, "lng": -46.63839}}, {"dataset": "aster30m", "elevation": 807.0, "location": {"lat": -23.569813, "lng": -46.637499}}, {"dataset": "aster30m", "elevation": 750.0, "location": {"lat": -23.539161, "lng": -46.664803}}, {"dataset": "aster30m", "elevation": 726.0, "location": {"lat": -23.524446, "lng": -46.659219}}, {"dataset": "aster30m", "elevation": 729.0, "location": {"lat": -23.527859, "lng": -46.65274}}, {"dataset": "aster30m", "elevation": 732.0, "location": {"lat": -23.519172, "lng": -46.651055}}, {"dataset": "aster30m", "elevation": 726.0, "location": {"lat": -23.522437, "lng": -46.637832}}, {"dataset": "aster30m", "elevation": 727.0, "location": {"lat": -23.522605, "lng": -46.637205}}, {"dataset": "aster30m", "elevation": 732.0, "location": {"lat": -23.529653, "lng": -46.641418}}, {"dataset": "aster30m", "elevation": 748.0, "location": {"lat": -23.530306, "lng": -46.652286}}, {"dataset": "aster30m", "elevation": 748.0, "location": {"lat": -23.529695, "lng": -46.651328}}, {"dataset": "aster30m", "elevation": 751.0, "location": {"lat": -23.53427, "lng": -46.641469}}, {"dataset": "aster30m", "elevation": 729.0, "location": {"lat": -23.527601, "lng": -46.637653}}, {"dataset": "aster30m", "elevation": 741.0, "location": {"lat": -23.528703, "lng": -46.643392}}, {"dataset": "aster30m", "elevation": 731.0, "location": {"lat": -23.526891, "lng": -46.648162}}, {"dataset": "aster30m", "elevation": 732.0, "location": {"lat": -23.525109, "lng": -46.649206}}, {"dataset": "aster30m", "elevation": 728.0, "location": {"lat": -23.550754, "lng": -46.62326}}, {"dataset": "aster30m", "elevation": 736.0, "location": {"lat": -23.551806, "lng": -46.622332}}, {"dataset": "aster30m", "elevation": 722.0, "location": {"lat": -23.537266, "lng": -46.62132}}, {"dataset": "aster30m", "elevation": 721.0, "location": {"lat": -23.536518, "lng": -46.627183}}, {"dataset": "aster30m", "elevation": 724.0, "location": {"lat": -23.53621, "lng": -46.627042}}, {"dataset": "aster30m", "elevation": 752.0, "location": {"lat": -23.534183, "lng": -46.637052}}, {"dataset": "aster30m", "elevation": 751.0, "location": {"lat": -23.53429, "lng": -46.63639}}, {"dataset": "aster30m", "elevation": 748.0, "location": {"lat": -23.534304, "lng": -46.636765}}, {"dataset": "aster30m", "elevation": 755.0, "location": {"lat": -23.534868, "lng": -46.639941}}, {"dataset": "aster30m", "elevation": 725.0, "location": {"lat": -23.533922, "lng": -46.626752}}, {"dataset": "aster30m", "elevation": 731.0, "location": {"lat": -23.531809, "lng": -46.629187}}, {"dataset": "aster30m", "elevation": 744.0, "location": {"lat": -23.531829, "lng": -46.636522}}, {"dataset": "aster30m", "elevation": 742.0, "location": {"lat": -23.531945, "lng": -46.634813}}, {"dataset": "aster30m", "elevation": 778.0, "location": {"lat": -23.552999, "lng": -46.634701}}, {"dataset": "aster30m", "elevation": 778.0, "location": {"lat": -23.552963, "lng": -46.634799}}, {"dataset": "aster30m", "elevation": 730.0, "location": {"lat": -23.52416, "lng": -46.630911}}, {"dataset": "aster30m", "elevation": 755.0, "location": {"lat": -23.569601, "lng": -46.630722}}, {"dataset": "aster30m", "elevation": 771.0, "location": {"lat": -23.554983, "lng": -46.635318}}, {"dataset": "aster30m", "elevation": 739.0, "location": {"lat": -23.529463, "lng": -46.665202}}, {"dataset": "aster30m", "elevation": 734.0, "location": {"lat": -23.568175, "lng": -46.604714}}, {"dataset": "aster30m", "elevation": 732.0, "location": {"lat": -23.568787, "lng": -46.606219}}, {"dataset": "aster30m", "elevation": 731.0, "location": {"lat": -23.569086, "lng": -46.606943}}, {"dataset": "aster30m", "elevation": 731.0, "location": {"lat": -23.56823, "lng": -46.607646}}, {"dataset": "aster30m", "elevation": 733.0, "location": {"lat": -23.567239, "lng": -46.605175}}, {"dataset": "aster30m", "elevation": 734.0, "location": {"lat": -23.56783, "lng": -46.606693}}, {"dataset": "aster30m", "elevation": 729.0, "location": {"lat": -23.56484, "lng": -46.611897}}, {"dataset": "aster30m", "elevation": 729.0, "location": {"lat": -23.564804, "lng": -46.611775}}, {"dataset": "aster30m", "elevation": 747.0, "location": {"lat": -23.557918, "lng": -46.603596}}, {"dataset": "aster30m", "elevation": 746.0, "location": {"lat": -23.557716, "lng": -46.602299}}, {"dataset": "aster30m", "elevation": 729.0, "location": {"lat": -23.564767, "lng": -46.611641}}, {"dataset": "aster30m", "elevation": 736.0, "location": {"lat": -23.556625, "lng": -46.607744}}, {"dataset": "aster30m", "elevation": 731.0, "location": {"lat": -23.556989, "lng": -46.608669}}, {"dataset": "aster30m", "elevation": 733.0, "location": {"lat": -23.566709, "lng": -46.609499}}, {"dataset": "aster30m", "elevation": 729.0, "location": {"lat": -23.562717, "lng": -46.611711}}, {"dataset": "aster30m", "elevation": 732.0, "location": {"lat": -23.567631, "lng": -46.608981}}, {"dataset": "aster30m", "elevation": 746.0, "location": {"lat": -23.564673, "lng": -46.602208}}, {"dataset": "aster30m", "elevation": 735.0, "location": {"lat": -23.566105, "lng": -46.605482}}, {"dataset": "aster30m", "elevation": 740.0, "location": {"lat": -23.55457, "lng": -46.609773}}, {"dataset": "aster30m", "elevation": 737.0, "location": {"lat": -23.553603, "lng": -46.608006}}, {"dataset": "aster30m", "elevation": 741.0, "location": {"lat": -23.557228, "lng": -46.615544}}, {"dataset": "aster30m", "elevation": 733.0, "location": {"lat": -23.554833, "lng": -46.615758}}, {"dataset": "aster30m", "elevation": 732.0, "location": {"lat": -23.554781, "lng": -46.616343}}, {"dataset": "aster30m", "elevation": 729.0, "location": {"lat": -23.556559, "lng": -46.615442}}, {"dataset": "aster30m", "elevation": 742.0, "location": {"lat": -23.554328, "lng": -46.61252}}, {"dataset": "aster30m", "elevation": 742.0, "location": {"lat": -23.552089, "lng": -46.612349}}, {"dataset": "aster30m", "elevation": 739.0, "location": {"lat": -23.557588, "lng": -46.622078}}, {"dataset": "aster30m", "elevation": 738.0, "location": {"lat": -23.553534, "lng": -46.622232}}, {"dataset": "aster30m", "elevation": 737.0, "location": {"lat": -23.553179, "lng": -46.613755}}, {"dataset": "aster30m", "elevation": 736.0, "location": {"lat": -23.559114, "lng": -46.624318}}, {"dataset": "aster30m", "elevation": 736.0, "location": {"lat": -23.558381, "lng": -46.622518}}, {"dataset": "aster30m", "elevation": 732.0, "location": {"lat": -23.556392, "lng": -46.622765}}, {"dataset": "aster30m", "elevation": 731.0, "location": {"lat": -23.558832, "lng": -46.615338}}, {"dataset": "aster30m", "elevation": 730.0, "location": {"lat": -23.552719, "lng": -46.6111}}, {"dataset": "aster30m", "elevation": 737.0, "location": {"lat": -23.557647, "lng": -46.622608}}, {"dataset": "aster30m", "elevation": 728.0, "location": {"lat": -23.556874, "lng": -46.626846}}, {"dataset": "aster30m", "elevation": 727.0, "location": {"lat": -23.557576, "lng": -46.626829}}, {"dataset": "aster30m", "elevation": 728.0, "location": {"lat": -23.553947, "lng": -46.625903}}, {"dataset": "aster30m", "elevation": 732.0, "location": {"lat": -23.554666, "lng": -46.627001}}, {"dataset": "aster30m", "elevation": 724.0, "location": {"lat": -23.55494, "lng": -46.628608}}, {"dataset": "aster30m", "elevation": 727.0, "location": {"lat": -23.558412, "lng": -46.626818}}, {"dataset": "aster30m", "elevation": 732.0, "location": {"lat": -23.549468, "lng": -46.625502}}, {"dataset": "aster30m", "elevation": 724.0, "location": {"lat": -23.544508, "lng": -46.630579}}, {"dataset": "aster30m", "elevation": 727.0, "location": {"lat": -23.549742, "lng": -46.628238}}, {"dataset": "aster30m", "elevation": 740.0, "location": {"lat": -23.550906, "lng": -46.628646}}, {"dataset": "aster30m", "elevation": 724.0, "location": {"lat": -23.534149, "lng": -46.625825}}, {"dataset": "aster30m", "elevation": 732.0, "location": {"lat": -23.552875, "lng": -46.626605}}, {"dataset": "aster30m", "elevation": 825.0, "location": {"lat": -23.555427, "lng": -46.663046}}, {"dataset": "aster30m", "elevation": 826.0, "location": {"lat": -23.555657, "lng": -46.662785}}, {"dataset": "aster30m", "elevation": 821.0, "location": {"lat": -23.555561, "lng": -46.663027}}, {"dataset": "aster30m", "elevation": 816.0, "location": {"lat": -23.554336, "lng": -46.664472}}], "status": "OK"}